
{"header" : {
  "cloc_url"           : "github.com/AlDanial/cloc",
  "cloc_version"       : "1.92",
  "elapsed_seconds"    : 0.406795978546143,
  "n_files"            : 197,
  "n_lines"            : 10612,
  "files_per_second"   : 484.272240605875,
  "lines_per_second"   : 26086.7868898962},
"TypeScript" :{
  "nFiles": 182,
  "blank": 961,
  "comment": 162,
  "code": 8505},
"JavaScript" :{
  "nFiles": 8,
  "blank": 17,
  "comment": 24,
  "code": 747},
"Markdown" :{
  "nFiles": 2,
  "blank": 22,
  "comment": 0,
  "code": 79},
"JSON" :{
  "nFiles": 1,
  "blank": 0,
  "comment": 0,
  "code": 61},
"SQL" :{
  "nFiles": 1,
  "blank": 4,
  "comment": 3,
  "code": 16},
"Bourne Shell" :{
  "nFiles": 2,
  "blank": 2,
  "comment": 0,
  "code": 6},
"TOML" :{
  "nFiles": 1,
  "blank": 0,
  "comment": 2,
  "code": 1},
"SUM": {
  "blank": 1006,
  "comment": 191,
  "code": 9415,
  "nFiles": 197} }
